django_jsheet/__init__.py
django_jsheet/manage.py
django_jsheet/src/core/__init__.py
django_jsheet/src/core/constats.py
django_jsheet/src/core/django_sheet.py
django_jsheet/src/core/views.py
django_jsheet/src/templatetags/__init__.py
django_jsheet/src/templatetags/jsheet.py
django_jsheet/src/templatetags/jspread_import.py
django_jsheet-0.3.9.data/data/libs/assets/constats.json
django_jsheet-0.3.9.data/data/libs/assets/fetch_js.js
django_jsheet-0.3.9.data/data/libs/libs/index.js
django_jsheet-0.3.9.data/data/libs/libs/jspreadsheet.css
django_jsheet-0.3.9.data/data/libs/libs/jspreadsheet.datatables.css
django_jsheet-0.3.9.data/data/libs/libs/jspreadsheet.theme.css
django_jsheet-0.3.9.data/data/libs/libs/jsuites.css
django_jsheet-0.3.9.data/data/libs/libs/jsuites.js
django_jsheet-0.3.9.dist-info/LICENSE
django_jsheet-0.3.9.dist-info/METADATA
django_jsheet-0.3.9.dist-info/WHEEL
django_jsheet-0.3.9.dist-info/top_level.txt
django_jsheet-0.3.9.dist-info/RECORD
