Metadata-Version: 2.1
Name: django-jsheet
Version: 0.3.9
Summary: Little tools to render a simple spreadsheet in webpage
Home-page: https://github.com/shadMod/django-jsheet
Download-URL: https://github.com/shadMod/django-jsheet/archive/refs/tags/0.3.9.tar.gz
Author: shadMod
Author-email: support@shadmod.it
Project-URL: Documentation, https://docs.shadmod.it/django_jsheet/index
Project-URL: GitHub, https://github.com/shadMod/django-jsheet/
Project-URL: Bug Tracker, https://github.com/shadMod/django-jsheet/issues/
Classifier: Development Status :: 4 - Beta
Classifier: Intended Audience :: Developers
Classifier: License :: OSI Approved :: MIT License
Classifier: Operating System :: OS Independent
Classifier: Programming Language :: Python :: 3
Classifier: Programming Language :: Python :: 3.8
Classifier: Programming Language :: Python :: 3.9
Classifier: Programming Language :: Python :: 3.10
Classifier: Programming Language :: Python :: 3.11
Requires-Python: >=3.8
License-File: LICENSE
